[
  {
    "id": "RASH0",
    "pa_ess_loc": "RASH",
    "pa_ess_zone": "m",
    "line_number": "2",
    "gtfs_stop_id": "70261",
    "direction_id": 0,
    "headsign": "Mattapan",
    "route_id": "Mattapan",
    "type": "single"
  },
  {
    "gtfs_stop_id": "70263",
    "pa_ess_loc": "MCED",
    "pa_ess_zone": "s",
    "headsign": "Mattapan",
    "direction_id": 0,
    "id": "MCED0",
    "route_id": "Mattapan",
    "type": "countdown"
  },
  {
    "gtfs_stop_id": "70264",
    "pa_ess_loc": "MCED",
    "pa_ess_zone": "n",
    "headsign": "Ashmont",
    "id": "MCED1",
    "direction_id": 1,
    "route_id": "Mattapan",
    "type": "countdown"
  },
  {
    "gtfs_stop_id": "70265",
    "pa_ess_loc": "MBUT",
    "pa_ess_zone": "s",
    "headsign": "Mattapan",
    "id": "MBUT0",
    "direction_id": 0,
    "route_id": "Mattapan",
    "type": "countdown"
  },
  {
    "gtfs_stop_id": "70266",
    "pa_ess_loc": "MBUT",
    "pa_ess_zone": "s",
    "route_id": "Mattapan",
    "id":  "MBUT1",
    "direction_id": 1,
    "type": "countdown"
  },
  {
    "gtfs_stop_id": "70267",
    "pa_ess_loc": "MMIL",
    "pa_ess_zone": "s",
    "headsign": "Mattapan",
    "direction_id": 0,
    "id": "MMIL0",
    "route_id": "Mattapan",
    "type": "countdown"
  },
  {
    "gtfs_stop_id": "70268",
    "pa_ess_loc": "MMIL",
    "pa_ess_zone": "n",
    "headsign": "Ashmont",
    "id": "MMIL1",
    "direction_id": 1,
    "route_id": "Mattapan",
    "type": "countdown"
  },
  {
    "gtfs_stop_id": "70269",
    "pa_ess_loc": "MCEN",
    "pa_ess_zone": "s",
    "headsign": "Mattapan",
    "direction_id": 0,
    "id": "MCEN0",
    "route_id": "Mattapan",
    "type": "countdown"
  },
  {
    "gtfs_stop_id": "70270",
    "pa_ess_loc": "MCEN",
    "pa_ess_zone": "n",
    "headsign": "Ashmont",
    "id": "MCEN1",
    "direction_id": 1,
    "route_id": "Mattapan",
    "type": "countdown"
  },
  {
    "gtfs_stop_id": "70271",
    "pa_ess_loc": "MVAL",
    "pa_ess_zone": "s",
    "headsign": "Mattapan",
    "direction_id": 0,
    "id": "MVAL0",
    "route_id": "Mattapan",
    "type": "countdown"
  },
  {
    "gtfs_stop_id": "70272",
    "pa_ess_loc": "MVAL",
    "pa_ess_zone": "n",
    "headsign": "Ashmont",
    "id": "MVAL1",
    "direction_id": 1,
    "route_id": "Mattapan",
    "type": "countdown"
  },
  {
    "gtfs_stop_id": "70273",
    "pa_ess_loc": "MCAP",
    "pa_ess_zone": "s",
    "headsign": "Mattapan",
    "direction_id": 0,
    "id": "MCAP0",
    "route_id": "Mattapan",
    "type": "countdown"
  },
  {
    "gtfs_stop_id": "70274",
    "pa_ess_loc": "MCAP",
    "pa_ess_zone": "n",
    "headsign": "Ashmont",
    "id": "MCAP1",
    "direction_id": 1,
    "route_id": "Mattapan",
    "type": "countdown"
  },
  {
    "gtfs_stop_id": "70275",
    "pa_ess_loc": "MMAT",
    "pa_ess_zone": "s",
    "headsign": "Mattapan",
    "direction_id": 0,
    "id": "MMAT0",
    "route_id": "Mattapan",
    "type": "countdown"
  },
  {
    "gtfs_stop_id": "70276",
    "pa_ess_loc": "MMAT",
    "pa_ess_zone": "n",
    "headsign": "Ashmont",
    "id": "MMAT1",
    "direction_id": 1,
    "route_id": "Mattapan",
    "type": "countdown"
  }
]
